pipswl/__init__.py
pipswl/downloader.py
pipswl-1.3.1.dist-info/METADATA
pipswl-1.3.1.dist-info/WHEEL
pipswl-1.3.1.dist-info/top_level.txt
pipswl-1.3.1.dist-info/RECORD
