Metadata-Version: 2.4
Name: pipswl
Version: 1.3.1
Summary: Steam Workshop Download List
Author: lesUchiha
Project-URL: GitHub, https://github.com/lesUchiha/pip-swl
Requires-Python: >=3.7
Requires-Dist: requests
Requires-Dist: tqdm
